{
  "Some formulas contain cyclic references": {
    "window_title": "Static",
    "window_text": "Некоторые формулы содержат циклические ссылки",
    "message": "Some formulas contain cyclic references. Clicked: 'ОК'",
    "button_title": "Button",
    "button_name": "ОК"
  },
  "The author advises opening  file for reading only": {
    "window_title": "Static",
    "window_text": "только для чтения, если вносить изменения не требуется.",
    "message": "The author advises opening  file for reading only. Clicked: 'ОК'",
    "button_title": "Button",
    "button_name": "Д&а"
  },
  "Invalid reference": {
    "window_title": "Static",
    "window_text": "Недопустимая ссылка. Ссылка для названий, значений",
    "message": "Invalid reference. Clicked: 'ОК'",
    "button_title": "Button",
    "button_name": "ОК"
  }
}
